terminaltables/__init__.py
terminaltables/ascii_table.py
terminaltables/base_table.py
terminaltables/build.py
terminaltables/github_table.py
terminaltables/other_tables.py
terminaltables/terminal_io.py
terminaltables/width_and_alignment.py
terminaltables-3.1.9.dist-info/entry_points.txt
terminaltables-3.1.9.dist-info/LICENSE
terminaltables-3.1.9.dist-info/WHEEL
terminaltables-3.1.9.dist-info/METADATA
terminaltables-3.1.9.dist-info/RECORD
