Metadata-Version: 2.1
Name: terminaltables
Version: 3.1.9
Summary: Generate simple tables in terminals from a nested list of strings.
Home-page: https://github.com/matthewdeanmartin/terminaltables
License: MIT
Keywords: Shell,Bash,ANSI,ASCII,terminal,tables
Author: Robpol86
Author-email: robpol86@gmail.com
Requires-Python: >=2.6
Classifier: Development Status :: 5 - Production/Stable
Classifier: Environment :: Console
Classifier: Environment :: MacOS X
Classifier: Environment :: Win32 (MS Windows)
Classifier: Intended Audience :: Developers
Classifier: License :: OSI Approved :: MIT License
Classifier: Operating System :: MacOS :: MacOS X
Classifier: Operating System :: Microsoft :: Windows
Classifier: Operating System :: POSIX
Classifier: Operating System :: POSIX :: Linux
Classifier: Programming Language :: Python :: 2
Classifier: Programming Language :: Python :: 2.6
Classifier: Programming Language :: Python :: 2.7
Classifier: Programming Language :: Python :: 3
Classifier: Programming Language :: Python :: 3.10
Classifier: Programming Language :: Python :: 3.3
Classifier: Programming Language :: Python :: 3.4
Classifier: Programming Language :: Python :: 3.5
Classifier: Programming Language :: Python :: 3.6
Classifier: Programming Language :: Python :: 3.7
Classifier: Programming Language :: Python :: 3.8
Classifier: Programming Language :: Python :: 3.9
Classifier: Programming Language :: Python :: Implementation :: PyPy
Classifier: Topic :: Software Development :: Libraries
Classifier: Topic :: Terminals
Classifier: Topic :: Text Processing :: Markup
Project-URL: Bug Tracker, https://github.com/matthewdeanmartin/terminaltables/issues
Project-URL: Change Log, https://github.com/matthewdeanmartin/terminaltables/blob/master/CHANGELOG.MD
Project-URL: Documentation, https://github.com/matthewdeanmartin/terminaltables
Project-URL: Repository, https://github.com/matthewdeanmartin/terminaltables
